tg/__init__.py
tg/app.py
tg/chatgpt/__init__.py
tg/chatgpt/chatgpt.py
tg/chatgpt/utils.py
tg/config.py
tg/speech_to_text/__init__.py
tg/speech_to_text/google_stt.py
tg/speech_to_text/speech_recognition.py
tg/speech_to_text/utils.py
tg/speech_to_text/whisper_stt.py
tg/tests/test_chatgpt.py
tg/tests/test_circular_queue.py
tg/tests/test_text_to_speech.py
tg/text_to_speech/__init__.py
tg/text_to_speech/azure_tts.py
tg/text_to_speech/base_tts.py
tg/text_to_speech/google_tts.py
tg/text_to_speech/text_to_speech.py
tg/text_to_speech/utils.py
talkgpt-0.1.0.dist-info/WHEEL
talkgpt-0.1.0.dist-info/METADATA
talkgpt-0.1.0.dist-info/licenses/LICENSE
talkgpt-0.1.0.dist-info/RECORD
